[
  {
    "date": "2026-04-03",
    "revenue": 119937.65,
    "orders": 131,
    "cogs": 38060.62,
    "fees_commission": 2918.85,
    "fees_fba": 7628.7,
    "fees_closing": 3242.64,
    "fees_total": 13790.19,
    "ad_spend": 0,
    "sessions": 2931,
    "conversion_pct": 4.5
  },
  {
    "date": "2026-04-04",
    "revenue": 92168.91,
    "orders": 109,
    "cogs": 31428.85,
    "fees_commission": 2731.59,
    "fees_fba": 8002.76,
    "fees_closing": 3568.32,
    "fees_total": 14302.67,
    "ad_spend": 0,
    "sessions": 2393,
    "conversion_pct": 4.55
  },
  {
    "date": "2026-04-05",
    "revenue": 98168.96,
    "orders": 111,
    "cogs": 32005.53,
    "fees_commission": 3007.85,
    "fees_fba": 8688.34,
    "fees_closing": 3379.52,
    "fees_total": 15075.71,
    "ad_spend": 0,
    "sessions": 2659,
    "conversion_pct": 4.17
  },
  {
    "date": "2026-04-06",
    "revenue": 84853.0,
    "orders": 117,
    "cogs": 30547.08,
    "fees_commission": 4965.49,
    "fees_fba": 8155.0,
    "fees_closing": 3953.0,
    "fees_total": 17073.49,
    "ad_spend": 0,
    "sessions": 0,
    "conversion_pct": 0
  }
]